{
  "name": "placeholderoldie",
  "title": "jQuery placeholderoldie",
  "description": "Add placeholders in old version of IE.",
  "keywords": [
    "jquery",
    "placeholder",
    "plugins",
    "Internet Explorer"
  ],
  "version": "1.0.0",
  "author": {
    "name": "Murilo Siqueira",
    "url": "https://github.com/msv2079"
  },
  "maintainers": [
    {
      "name": "Murilo Siqueira",
      "email": "msv2079@gmail.com",
      "url": "https://github.com/msv2079"
    }
  ],
  "licenses": [
    {
      "type": "MIT",
      "url": "http://opensource.org/licenses/MIT"
    }
  ],
  "docs": "https://github.com/msv2079/placeholderoldie/#README.md",
  "download": "https://github.com/msv2079/placeholderoldie/archive/master.zip",
  "dependencies": {
    "jquery": ">=1.6.3"
  }
}